ayaka_who_is_suspect/__init__.py
ayaka_who_is_suspect/data.py
ayaka_who_is_suspect/utils.py
nonebot_plugin_ayaka_who_is_suspect-0.2.0.dist-info/LICENSE
nonebot_plugin_ayaka_who_is_suspect-0.2.0.dist-info/WHEEL
nonebot_plugin_ayaka_who_is_suspect-0.2.0.dist-info/METADATA
nonebot_plugin_ayaka_who_is_suspect-0.2.0.dist-info/RECORD
