Metadata-Version: 2.1
Name: nonebot-plugin-ayaka-who-is-suspect
Version: 0.2.0
Summary: 谁是卧底
Home-page: https://github.com/bridgeL/nonebot-plugin-ayaka-who-is-suspect
License: MIT
Author: Su
Author-email: wxlxy316@163.com
Requires-Python: >=3.8,<4.0
Classifier: License :: OSI Approved :: MIT License
Classifier: Programming Language :: Python :: 3
Classifier: Programming Language :: Python :: 3.8
Classifier: Programming Language :: Python :: 3.9
Classifier: Programming Language :: Python :: 3.10
Requires-Dist: nonebot-adapter-onebot (>=2.1.3,<3.0.0)
Requires-Dist: nonebot-plugin-ayaka (>=0.5.1,<0.6.0)
Requires-Dist: nonebot2 (>=2.0.0b5,<3.0.0)
Project-URL: Repository, https://github.com/bridgeL/nonebot-plugin-ayaka-who-is-suspect
